LICENSE
MANIFEST.in
README.md
setup.cfg
setup.py
GeoUK.egg-info/PKG-INFO
GeoUK.egg-info/SOURCES.txt
GeoUK.egg-info/dependency_links.txt
GeoUK.egg-info/requires.txt
GeoUK.egg-info/top_level.txt
geouk/__init__.py
geouk/client.py
geouk/exceptions.py
geouk/resources.py