Metadata-Version: 2.1
Name: GeoUK
Version: 0.0.6
Summary: The GeoUK Python library provides a pythonic interface to the GeoUK API.
Home-page: https://github.com/GetmeUK/geouk-python
Author: Anthony Blackshaw
Author-email: ant@getme.co.uk
Maintainer: Anthony Blackshaw
Maintainer-email: ant@getme.co.uk
License: MIT
Keywords: api geouk
Platform: UNKNOWN
Classifier: Development Status :: 4 - Beta
Classifier: Intended Audience :: Developers
Classifier: Topic :: Database
Classifier: License :: OSI Approved :: MIT License
Classifier: Operating System :: MacOS :: MacOS X
Classifier: Operating System :: Microsoft :: Windows
Classifier: Operating System :: POSIX
Classifier: Programming Language :: Python :: 3.7
